cesnet_tszoo/__init__.py
cesnet_tszoo/annotation.py
cesnet_tszoo/benchmarks.py
cesnet_tszoo/version.py
cesnet_tszoo/configs/__init__.py
cesnet_tszoo/configs/base_config.py
cesnet_tszoo/configs/config_loading.py
cesnet_tszoo/configs/config_updater.py
cesnet_tszoo/configs/disjoint_time_based_config.py
cesnet_tszoo/configs/series_based_config.py
cesnet_tszoo/configs/time_based_config.py
cesnet_tszoo/configs/handlers/__init__.py
cesnet_tszoo/configs/handlers/series_based_handler.py
cesnet_tszoo/configs/handlers/time_based_handler.py
cesnet_tszoo/datasets/__init__.py
cesnet_tszoo/datasets/cesnet_database.py
cesnet_tszoo/datasets/cesnet_dataset.py
cesnet_tszoo/datasets/datasets.py
cesnet_tszoo/datasets/datasets_constants.py
cesnet_tszoo/datasets/disjoint_time_based_cesnet_dataset.py
cesnet_tszoo/datasets/loaders.py
cesnet_tszoo/datasets/series_based_cesnet_dataset.py
cesnet_tszoo/datasets/time_based_cesnet_dataset.py
cesnet_tszoo/files/__init__.py
cesnet_tszoo/files/annotations_metadata.csv
cesnet_tszoo/files/utils.py
cesnet_tszoo/files/annotation_files/__init__.py
cesnet_tszoo/files/annotation_files/device_type_ip_address_full.csv
cesnet_tszoo/files/benchmark_files/0197980a87c0.yaml
cesnet_tszoo/files/benchmark_files/080582bcd519.yaml
cesnet_tszoo/files/benchmark_files/084f368f4c82.yaml
cesnet_tszoo/files/benchmark_files/095f847ca755.yaml
cesnet_tszoo/files/benchmark_files/09de83e89e42.yaml
cesnet_tszoo/files/benchmark_files/0d523e69c328.yaml
cesnet_tszoo/files/benchmark_files/0f4fbc0419ce.yaml
cesnet_tszoo/files/benchmark_files/15737f3fceec.yaml
cesnet_tszoo/files/benchmark_files/16274e0b44af.yaml
cesnet_tszoo/files/benchmark_files/18d04cab63e4.yaml
cesnet_tszoo/files/benchmark_files/2112383abab7.yaml
cesnet_tszoo/files/benchmark_files/22c5a8e8ffd3.yaml
cesnet_tszoo/files/benchmark_files/2439d12c2292.yaml
cesnet_tszoo/files/benchmark_files/2e92831cb502.yaml
cesnet_tszoo/files/benchmark_files/3687fb52c433.yaml
cesnet_tszoo/files/benchmark_files/394603854070.yaml
cesnet_tszoo-2.0.0.dist-info/licenses/LICENSE
cesnet_tszoo-2.0.0.dist-info/METADATA
cesnet_tszoo-2.0.0.dist-info/WHEEL
cesnet_tszoo-2.0.0.dist-info/top_level.txt
cesnet_tszoo-2.0.0.dist-info/RECORD
