Metadata-Version: 2.4
Name: cesnet_tszoo
Version: 2.0.0
Summary: A toolkit for working with large time series network traffic datasets.
Author-email: Milan Kureš <kuresmil@fit.cvut.cz>, Josef Koumar <josef.koumar@fit.cvut.cz>
Maintainer-email: Milan Kureš <kuresmil@fit.cvut.cz>, Josef Koumar <josef.koumar@fit.cvut.cz>
License-Expression: BSD-3-Clause
Project-URL: Homepage, https://github.com/CESNET/cesnet-tszoo
Project-URL: Documentation, https://cesnet.github.io/cesnet-tszoo/
Project-URL: Bug Tracker, https://github.com/CESNET/cesnet-tszoo/issues
Keywords: datasets,machine learning,time series,traffic forecasting,traffic classification,traffic anomaly detection,traffic similarity search
Classifier: Programming Language :: Python :: 3.10
Classifier: Intended Audience :: Science/Research
Classifier: Operating System :: OS Independent
Requires-Python: >=3.10
License-File: LICENSE
Requires-Dist: numpy
Requires-Dist: pandas
Requires-Dist: scikit-learn
Requires-Dist: tables>=3.10.0
Requires-Dist: torch>=1.10
Requires-Dist: tqdm
Requires-Dist: nbformat>=4.2.0
Requires-Dist: plotly
Requires-Dist: PyYAML
Requires-Dist: requests
Requires-Dist: matplotlib
Requires-Dist: packaging
Requires-Dist: importlib
Provides-Extra: dev
Requires-Dist: build; extra == "dev"
Requires-Dist: mkdocs-autorefs; extra == "dev"
Requires-Dist: mkdocs-material-extensions; extra == "dev"
Requires-Dist: mkdocs-material; extra == "dev"
Requires-Dist: mkdocs; extra == "dev"
Requires-Dist: mkdocstrings-python; extra == "dev"
Requires-Dist: mkdocstrings; extra == "dev"
Requires-Dist: twine; extra == "dev"
Dynamic: license-file
